{
  "version": 1,
  "skills": {
    "Clean Architecture & Testing": {
      "source": "duyxyz/SkillAnti",
      "sourceType": "github",
      "computedHash": "1c925669e9c186895eb0249f71100139b7edec694fcb9d2913a01ea83147a639"
    },
    "Code Quality & Debugging Excellence": {
      "source": "duyxyz/SkillAnti",
      "sourceType": "github",
      "computedHash": "fb5b6036831a6bc7984fe435e73bfc1d36d97936f8ce4b369d218cdb4600fb01"
    },
    "Strict Command Adherence & Concise Communication": {
      "source": "duyxyz/SkillAnti",
      "sourceType": "github",
      "computedHash": "00c3539f89cd41a8a429e5293df26a225a0412306cbacb4452fcfa59c69600a3"
    }
  }
}
